aristotePV/__init__.py
aristotePV/aristote.py
aristotePV/confFiles/aristote.md
aristotePV/confFiles/conftracker.ods
aristotePV/confFiles/confvector.ods
aristote_malo-1.9.5.data/data/my_data/DataPrevision.pkl
aristote_malo-1.9.5.dist-info/METADATA
aristote_malo-1.9.5.dist-info/WHEEL
aristote_malo-1.9.5.dist-info/top_level.txt
aristote_malo-1.9.5.dist-info/RECORD
