Metadata-Version: 2.1
Name: aristote-malo
Version: 1.9.5
Summary: Programme de prévision de production électrique d'une centrale PV
Author: Malo FRACKOWIAK
Author-email: malo.frackowiak.sta@sylfen.com
Classifier: Programming Language :: Python :: 3
Classifier: License :: OSI Approved :: MIT License
Classifier: Operating System :: OS Independent
Requires-Python: >=3.8
Requires-Dist: dorianUtils (==5.1.2)
Requires-Dist: geopy (==2.2.0)
Requires-Dist: tzwhere (==3.0.3)
Requires-Dist: requests (==2.28.1)
Requires-Dist: urllib3 (==1.26.10)
Requires-Dist: pygrib (==2.1.4)
Requires-Dist: numpy (==1.23.1)
Requires-Dist: scikit-learn (==1.1.1)
